<?xml version="1.0" encoding="UTF-8"?>
<manifest xmlns="http://www.overheid.nl/2017/lvbb"
    xmlns:xsi="http://www.w3.org/2001/XMLSchema-instance"
    xmlns:stop="http://www.overheid.nl/2017/stop"
    xsi:schemaLocation="http://www.overheid.nl/2017/lvbb ../lvbb/lvbb-transport.xsd">
    <bestand>
        <bestandsnaam>GIO_001-werkingsgebied_projectbesluit_zuidas_20180320.geom.0.xml</bestandsnaam>
        <contentType>application/xml</contentType>
    </bestand>
    <bestand>
        <bestandsnaam>GIO_002-NL.IMRO.0363.K1402BPGST-VG01.bestemming_verkeer.geom.0.xml</bestandsnaam>
        <contentType>application/xml</contentType>
    </bestand>
    <bestand>
        <bestandsnaam>manifest.xml</bestandsnaam>
        <contentType>application/xml</contentType>
    </bestand>
    <bestand>
        <bestandsnaam>NL.IMRO.0363.K1402BPGST-VG01.bestemming_verkeer.geom.0.gml</bestandsnaam>
        <contentType>application/gml+xml</contentType>
    </bestand>
    <bestand>
        <bestandsnaam>opdracht.xml</bestandsnaam>
        <contentType>application/xml</contentType>
    </bestand>
    <bestand>
        <bestandsnaam>opManifest.xml</bestandsnaam>
        <contentType>application/xml</contentType>
    </bestand>
    <bestand>
        <bestandsnaam>opOpdracht.xml</bestandsnaam>
        <contentType>application/xml</contentType>
    </bestand>
    <bestand>
        <bestandsnaam>opProjectBesluit.xml</bestandsnaam>
        <contentType>application/xml</contentType>
    </bestand>
    <bestand>
        <bestandsnaam>owGebiedsaanwijzingen-Zuidasdok.xml</bestandsnaam>
        <contentType>application/xml</contentType>
    </bestand>
    <bestand>
        <bestandsnaam>owLocatie.xml</bestandsnaam>
        <contentType>application/xml</contentType>
    </bestand>
    <bestand>
        <bestandsnaam>owManifest.xml</bestandsnaam>
        <contentType>application/xml</contentType>
    </bestand>
    <bestand>
        <bestandsnaam>owTekstdeel.xml</bestandsnaam>
        <contentType>application/xml</contentType>
    </bestand>
    <bestand>
        <bestandsnaam>werkingsgebied_projectbesluit_zuidas_20180320.geom.0.gml</bestandsnaam>
        <contentType>application/gml+xml</contentType>
    </bestand>
</manifest>
